{"Date":"2013-08-09","IC_buy":160,"IC_sell":160.15,"USD_buy":97.2,"USD_sell":97.8,"EUR_buy":129.81,"EUR_sell":130.61,"GBP_buy":150.74,"GBP_sell":151.67,"CHF_buy":105.57,"CHF_sell":106.22,"AUD_buy":88.02,"AUD_sell":88.56,"CAD_buy":93.34,"CAD_sell":93.92,"SGD_buy":77.05,"SGD_sell":77.53,"JPY_buy":10.09,"JPY_sell":10.15,"CNY_buy":15.88,"CNY_sell":15.98,"SEK_buy":14.94,"DKK_buy":17.41,"HKD_buy":12.53,"SAR_buy":25.92,"SAR_sell":26.08,"QAR_buy":26.69,"QAR_sell":26.86,"THB_buy":3.11,"THB_sell":3.13,"AED_buy":26.46,"AED_sell":26.63,"MYR_buy":29.87,"MYR_sell":30.05,"KPW_buy":8.73,"KPW_sell":8.79}